pylex/__init__.py
pylex/__main__.py
pylex/lexer.py
pylex/token.py
pylex/config/__init__.py
pylex/config/lexer_config.py
pylex/config/lexer_dict_config.py
pylex/config/token_defination.py
pylex/error/__init__.py
pylex/error/custom_exception.py
pylexer-1.0.0.dist-info/METADATA
pylexer-1.0.0.dist-info/RECORD
pylexer-1.0.0.dist-info/WHEEL
pylexer-1.0.0.dist-info/entry_points.txt
pylexer-1.0.0.dist-info/top_level.txt
tests/__init__.py
tests/test_lexer.py
