Metadata-Version: 2.1
Name: pylexer
Version: 1.0.0
Summary: A python implementation of a lexical analyzer which supports full scan, state based lexing and lookahead
Home-page: https://github.com/subhajeet2107/pylexer/
Author: Subhajeet Dey
Author-email: subhajeet2107@gmail.com
License: MIT License
Platform: UNKNOWN
Requires-Dist: pytest
Requires-Dist: six
